buisness_metrick.py
buisness_elf_unic-0.0.0.dist-info/METADATA
buisness_elf_unic-0.0.0.dist-info/WHEEL
buisness_elf_unic-0.0.0.dist-info/entry_points.txt
buisness_elf_unic-0.0.0.dist-info/top_level.txt
buisness_elf_unic-0.0.0.dist-info/RECORD
