Metadata-Version: 2.1
Name: buisness_elf_unic
Version: 0.0.0
Summary: count roi
